expath/__init__.py
expath/__main__.py
expath/_download.py
expath/_types.py
expath/manager.py
expath/py.typed
expath/cli/__init__.py
expath/handlers/__init__.py
expath/handlers/__init__.pyi
expath/handlers/_base.py
expath/handlers/_io.py
expath/handlers/_os.py
expath/handlers/env.py
expath/handlers/http.py
expath/handlers/meta.py
expath/handlers/onedrive.py
expath/handlers/wandb.py
expath/lock/__init__.py
expath/lock/_exceptions.py
expath/lock/_flags.py
expath/lock/_lock.py
expath/lock/ops.py
expath/lock/ops_posix.py
expath/lock/ops_win32.py
expath-0.0.6.dist-info/licenses/LICENSE
expath-0.0.6.dist-info/METADATA
expath-0.0.6.dist-info/WHEEL
expath-0.0.6.dist-info/entry_points.txt
expath-0.0.6.dist-info/top_level.txt
expath-0.0.6.dist-info/RECORD
