Metadata-Version: 2.4
Name: expath
Version: 0.0.6
Summary: Standalone version of the expath module from the unipercept library.
Author-email: Kurt Stolle <kurt@khws.io>
Keywords: perception,computer vision,deep learning,object detection,instance segmentation,semantic segmentation
Classifier: Development Status :: 4 - Beta
Classifier: Programming Language :: Python
Classifier: Programming Language :: Python :: 3.12
Classifier: Programming Language :: Python :: 3.13
Classifier: Programming Language :: Python :: Implementation :: CPython
Classifier: Operating System :: OS Independent
Classifier: Intended Audience :: Developers
Classifier: Topic :: Software Development :: Libraries :: Python Modules
Requires-Python: >=3.12
License-File: LICENSE
Requires-Dist: tqdm
Provides-Extra: wandb
Requires-Dist: wandb; extra == "wandb"
Dynamic: license-file
